demox12/__init__.py
demox12/charniroad.png
demox12/index.html
demox12/p1/charniroad.png
demox12/p1/index.html
demox12/p2/index.html
demox12-0.1.3.dist-info/METADATA
demox12-0.1.3.dist-info/WHEEL
demox12-0.1.3.dist-info/top_level.txt
demox12-0.1.3.dist-info/RECORD
