Metadata-Version: 2.4
Name: demox12
Version: 0.1.3
Summary: Distributes PDFs, images, docs, and other assets
Author: FirstRayofSun
License: MIT
Requires-Python: >=3.8
